giniindex/__init__.py
giniindex/fetch_pdf.py
ranker/__init__.py
ranker/fetch_pdf.py
giniindex-0.1.0.dist-info/METADATA
giniindex-0.1.0.dist-info/WHEEL
giniindex-0.1.0.dist-info/top_level.txt
giniindex-0.1.0.dist-info/RECORD
