Metadata-Version: 2.1
Name: giniindex
Version: 0.1.0
Summary: A python package with a ranker function
Home-page: 
Author: Sam Manuel
Author-email: 
Classifier: Programming Language :: Python :: 3
Classifier: License :: OSI Approved :: MIT License
Classifier: Operating System :: OS Independent
Requires-Python: >=3.6
